moneyterm/__init__.py
moneyterm/__main__.py
moneyterm/screens/__init__.py
moneyterm/screens/addlabelscreen.py
moneyterm/screens/confirmscreen.py
moneyterm/screens/quicklabelscreen.py
moneyterm/screens/renamelabelscreen.py
moneyterm/screens/tabbedcontentscreen.py
moneyterm/screens/transactiondetailscreen.py
moneyterm/screens/transactionsplitscreen.py
moneyterm/tcss/addlabelscreen.tcss
moneyterm/tcss/confirmscreen.tcss
moneyterm/tcss/moneyterm.tcss
moneyterm/tcss/quicklabelscreen.tcss
moneyterm/tcss/renamelabelscreen.tcss
moneyterm/tcss/tabbedcontentscreen.tcss
moneyterm/tcss/transactiondetailscreen.tcss
moneyterm/tcss/transactionsplitscreen.tcss
moneyterm/utils/__init__.py
moneyterm/utils/config.py
moneyterm/utils/data_importer.py
moneyterm/utils/ledger.py
moneyterm/widgets/budgeter.py
moneyterm/widgets/config.py
moneyterm/widgets/labeler.py
moneyterm/widgets/overviewwidget.py
moneyterm/widgets/scopeselectbar.py
moneyterm/widgets/transactiontable.py
moneyterm/widgets/trends.py
moneyterm-0.0.5.dist-info/METADATA
moneyterm-0.0.5.dist-info/WHEEL
moneyterm-0.0.5.dist-info/entry_points.txt
moneyterm-0.0.5.dist-info/RECORD
