Metadata-Version: 2.1
Name: moneyterm
Version: 0.0.5
Summary: Terminal finance dashboard.
License: MIT
Author: Chris
Author-email: 741258+github@pm.me
Requires-Python: >=3.10,<4.0
Classifier: License :: OSI Approved :: MIT License
Classifier: Programming Language :: Python :: 3
Classifier: Programming Language :: Python :: 3.10
Classifier: Programming Language :: Python :: 3.11
Requires-Dist: appdirs (>=1.4.4,<2.0.0)
Requires-Dist: ofxparse (>=0.21,<0.22)
Requires-Dist: python-dateutil (>=2.8.2,<3.0.0)
Requires-Dist: rich (>=13.7.0,<14.0.0)
Requires-Dist: textual (>=0.44.0,<0.45.0)
Requires-Dist: textual-plotext (>=0.2.1,<0.3.0)
